smos_walker/__init__.py
smos_walker/api/__init__.py
smos_walker/api/core.py
smos_walker/api/facade.py
smos_walker/api/tools.py
smos_walker/cli/__init__.py
smos_walker/cli/facade.py
smos_walker/config.py
smos_walker/constants.py
smos_walker/core/__init__.py
smos_walker/core/exception.py
smos_walker/core/node.py
smos_walker/core/visitors.py
smos_walker/data_reader/__init__.py
smos_walker/data_reader/facade.py
smos_walker/data_reader/reader.py
smos_walker/main.py
smos_walker/node_to_ndarray/__init__.py
smos_walker/node_to_ndarray/facade.py
smos_walker/node_to_ndarray/node_to_ndarray.py
smos_walker/remote/__init__.py
smos_walker/remote/fetch_remote_headers.py
smos_walker/typesystem_dynamic_decorator/__init__.py
smos_walker/typesystem_dynamic_decorator/dynamic_decorator.py
smos_walker/typesystem_dynamic_decorator/facade.py
smos_walker/typesystem_parser/__init__.py
smos_walker/typesystem_parser/core.py
smos_walker/typesystem_parser/facade.py
smos_walker/typesystem_parser/node_wrapper.py
smos_walker/typesystem_static_decorator/__init__.py
smos_walker/typesystem_static_decorator/enhanced_tree_converter.py
smos_walker/typesystem_static_decorator/facade.py
smos_walker/util.py
smos_walker/xml_reader/__init__.py
smos_walker/xml_reader/facade.py
smos_walker/xml_reader/node_wrapper.py
smos_walker-0.5.0.dist-info/WHEEL
smos_walker-0.5.0.dist-info/METADATA
smos_walker-0.5.0.dist-info/RECORD
