Metadata-Version: 2.1
Name: smos-walker
Version: 0.5.0
Summary: 
Author: Etienne Schalk
Author-email: eschalk@argans.eu
Requires-Python: >=3.10,<4.0
Classifier: Programming Language :: Python :: 3
Classifier: Programming Language :: Python :: 3.10
Classifier: Programming Language :: Python :: 3.11
Requires-Dist: lxml (>=4.9.2,<5.0.0)
Requires-Dist: numpy (>=1.24.2,<2.0.0)
Requires-Dist: tqdm (>=4.65.0,<5.0.0)
Requires-Dist: typing-extensions (>=4.5.0,<5.0.0)
Requires-Dist: xmlschema (>=2.2.0,<3.0.0)
